AUTHORS.rst
CONTRIBUTING.rst
HISTORY.rst
LICENSE
MANIFEST.in
README.rst
setup.cfg
setup.py
django_simple_referrals.egg-info/PKG-INFO
django_simple_referrals.egg-info/SOURCES.txt
django_simple_referrals.egg-info/dependency_links.txt
django_simple_referrals.egg-info/not-zip-safe
django_simple_referrals.egg-info/requires.txt
django_simple_referrals.egg-info/top_level.txt
referrals/__init__.py
referrals/admin.py
referrals/apps.py
referrals/fields.py
referrals/models.py
referrals/receivers.py
referrals/signals.py
referrals/urls.py
referrals/views.py
referrals/widgets.py
referrals/migrations/0001_initial.py
referrals/migrations/__init__.py
referrals/static/css/referrals.css
referrals/static/js/referrals.js
referrals/templates/referrals/base.html
referrals/templates/referrals/flat_referral_detail.html
referrals/templates/referrals/flat_referral_list.html
referrals/templates/referrals/multi_level_referral_detail.html
referrals/templates/referrals/multi_level_referral_list.html
referrals/templates/referrals/referral_token.html
referrals/templates/referrals/referral_widget.html
referrals/templates/referrals/referral_widget_min.html
referrals/templatetags/__init__.py
referrals/templatetags/referrals.py