Metadata-Version: 1.1
Name: django-simple-referrals
Version: 0.2
Summary: A simple application that allows you to generate referral links and track referrals
Home-page: https://github.com/narnikgamarnikus/django-simple-referrals
Author: Vladimir Myshkovski
Author-email: vladimirmyshkovski@gmail.com
License: MIT
Keywords: django-simple-referrals
Platform: UNKNOWN
Classifier: Development Status :: 3 - Alpha
Classifier: Framework :: Django :: 2.0
Classifier: Intended Audience :: Developers
Classifier: License :: OSI Approved :: BSD License
Classifier: Natural Language :: English
Classifier: Programming Language :: Python :: 2
Classifier: Programming Language :: Python :: 2.7
Classifier: Programming Language :: Python :: 3
Classifier: Programming Language :: Python :: 3.4
Classifier: Programming Language :: Python :: 3.5
Classifier: Programming Language :: Python :: 3.6
